historian_data_compression/__init__.py
historian_data_compression/historian_data_compression.py
historian_data_compression/examples/__init__.py
historian_data_compression/examples/example_1.py
historian_data_compression/examples/example_2.py
historian_data_compression-0.0.14.dist-info/LICENSE
historian_data_compression-0.0.14.dist-info/METADATA
historian_data_compression-0.0.14.dist-info/WHEEL
historian_data_compression-0.0.14.dist-info/top_level.txt
historian_data_compression-0.0.14.dist-info/RECORD
