Metadata-Version: 2.1
Name: historian_data_compression
Version: 0.0.14
Summary: Deadband and swinging door compression of historian data with Python.
Home-page: https://github.com/PVanhevel/
Author: Peter Vanhevel
Author-email: peter.vanhevel@gmail.com
License: MIT
Project-URL: Source, https://github.com/PVanhevel/historian_data_compression
Project-URL: Tracker, https://github.com/PVanhevel/historian_data_compression/issues
Keywords: python,historian,compression,deadband,swing door
Platform: any
Classifier: Development Status :: 5 - Production/Stable
Classifier: Operating System :: OS Independent
Classifier: Intended Audience :: Developers
Classifier: License :: OSI Approved :: MIT License
Classifier: Topic :: Software Development
Classifier: Typing :: Typed
Classifier: Programming Language :: Python :: 3
License-File: LICENSE
